{
  "folders":[
    {"id":"0", "label":"un", "parent":"", "depth":0, "childCount":1, "children":[]},
    {"id":"0/1", "label":"un", "parent":"0", "depth":1, "childCount":0, "children":[]}
  ],
  "files":[
    {"id":"0/2", "label": "1st babby", "parent":"0", "depth":1, "text":"the fuck is wrong with you people"},
    {"id":"0/2/1", "label": "grandbabby", "parent":"0/1", "depth":2, "text":"go off, king"}
  ],
  
  "data":{
    "id":"root",
    "label":"World",
    "root":"",
    "children":[
      {"id":"root/1","label":"party", "parent":"root", "text": "1. loot\n2. kill\n3. return"},
      {"id":"root/2","label":"places", "parent":"root", "text": "herp a derp"},
      {"id":"root/3","label":"items", "parent":"root", "text": "yolo bolo"},
      {"id":"root/4","label":"misc", "parent":"root", "text":""},
      {
        "id":"root/sub1",
        "label":"Events",
        "parent":"root",
        "children":[
          {"id":"root/sub1/1","label":"This year", "parent":"sub1", "text": "BIG ASS KITTIES"},
          {"id":"root/sub1/2","label":"This month", "parent":"sub1", "text": "it vaz ze yuce"},
          {"id":"root/sub1/3","label":"This week", "parent":"sub1", "text":""},
          {"id":"root/sub1/4","label":"Today", "parent":"sub1", "text":""}
        ]
      }
    ]
  }
}